SpineAtlas/Spine_Atlas.py
SpineAtlas/__init__.py
spineatlas-1.0.13.dist-info/licenses/LICENSE
spineatlas-1.0.13.dist-info/METADATA
spineatlas-1.0.13.dist-info/WHEEL
spineatlas-1.0.13.dist-info/top_level.txt
spineatlas-1.0.13.dist-info/RECORD
